astropayments/__init__.py
astropayments/api.py
astropayments/mockhandler.py
astropayments/batches/__init__.py
astropayments/batches/current/__init__.py
astropayments/batches/current/close/__init__.py
astropayments/batches/current/transactions/__init__.py
astropayments/batches/transactions/__init__.py
astropayments/customers/__init__.py
astropayments/customers/billing_schedules/__init__.py
astropayments/customers/billing_schedules/billing_schedule_rules/__init__.py
astropayments/customers/billing_schedules/billing_schedule_rules/bulk/__init__.py
astropayments/customers/bulk/__init__.py
astropayments/customers/disable/__init__.py
astropayments/customers/enable/__init__.py
astropayments/customers/payment_methods/__init__.py
astropayments/customers/transactions/__init__.py
astropayments/invoices/__init__.py
astropayments/invoices/bulk/__init__.py
astropayments/invoices/bulk/send/__init__.py
astropayments/invoices/cancel/__init__.py
astropayments/invoices/columns/__init__.py
astropayments/invoices/defaults/__init__.py
astropayments/invoices/nextnum/__init__.py
astropayments/invoices/payments/__init__.py
astropayments/invoices/send/__init__.py
astropayments/middleware/__init__.py
astropayments/middleware/webhook.py
astropayments/paymentengine/__init__.py
astropayments/paymentengine/devices/__init__.py
astropayments/paymentengine/devices/kick/__init__.py
astropayments/paymentengine/devices/settings/__init__.py
astropayments/paymentengine/devices/terminal_config/__init__.py
astropayments/paymentengine/payrequests/__init__.py
astropayments/paymentengine/payrequests/confirm/__init__.py
astropayments/products/__init__.py
astropayments/products/categories/__init__.py
astropayments/publickey/__init__.py
astropayments/tokens/__init__.py
astropayments/transactions/__init__.py
astropayments/transactions/receipts/__init__.py
astropayments/transactions/send/__init__.py
astropayments-2.1.4.2.dist-info/LICENSE.txt
astropayments-2.1.4.2.dist-info/METADATA
astropayments-2.1.4.2.dist-info/WHEEL
astropayments-2.1.4.2.dist-info/top_level.txt
astropayments-2.1.4.2.dist-info/RECORD
