Metadata-Version: 2.1
Name: astropayments
Version: 2.1.4.2
Summary: sdk for astropayments rest api
Home-page: https://api.goastro.com/
Author: astropayments
Author-email: integrations@goastro.com
License: UNKNOWN
Platform: UNKNOWN
Classifier: Programming Language :: Python :: 3
Classifier: License :: OSI Approved :: MIT License
Classifier: Operating System :: OS Independent
Requires-Python: >=3.6
License-File: LICENSE.txt
Requires-Dist: requests
